{"links": {"self": {"href": "data/repositories/dedalus-project/dedalus/issues/38/comments/45166447.json"}, "html": {"href": "#!/dedalus-project/dedalus/issues/38#comment-45166447"}}, "issue": {"links": {"self": {"href": "data/repositories/dedalus-project/dedalus/issues/38.json"}}, "type": "issue", "id": 38, "repository": {"links": {"self": {"href": "data/repositories/dedalus-project/dedalus.json"}, "html": {"href": "#!/dedalus-project/dedalus"}, "avatar": {"href": "data/bytebucket.org/ravatar/{1dc39ab6-2798-450d-af2f-e976f94b5794}ts=2009435"}}, "type": "repository", "name": "dedalus", "full_name": "dedalus-project/dedalus", "uuid": "{1dc39ab6-2798-450d-af2f-e976f94b5794}"}, "title": "Slow simulation NS2D over a biperiodic space?"}, "content": {"raw": "ns2d_rot.py, updated to set streamfunction gauge, use SBDF3, and separate startup loops from timing loops.", "markup": "markdown", "html": "<p>ns2d_rot.py, updated to set streamfunction gauge, use SBDF3, and separate startup loops from timing loops.</p>", "type": "rendered"}, "created_on": "2018-05-02T19:22:26.608856+00:00", "user": {"display_name": "Keaton Burns", "uuid": "{3d3e64f1-bf12-45df-b655-4543d8fb34c4}", "links": {"self": {"href": "https://api.bitbucket.org/2.0/users/%7B3d3e64f1-bf12-45df-b655-4543d8fb34c4%7D"}, "html": {"href": "https://bitbucket.org/%7B3d3e64f1-bf12-45df-b655-4543d8fb34c4%7D/"}, "avatar": {"href": "https://avatar-management--avatars.us-west-2.prod.public.atl-paas.net/557058:e31a7835-5317-4dfa-8551-f32a06f40279/40f33f99-2b75-4a17-a8c2-07c8d74c7480/128"}}, "nickname": "kburns", "type": "user", "account_id": "557058:e31a7835-5317-4dfa-8551-f32a06f40279"}, "updated_on": null, "type": "issue_comment", "id": 45166447}