{"changes": {"title": {"new": "Not able to install dedalus packages using pip3", "old": "Not able to install using dedalus packages pip3"}}, "links": {"self": {"href": "data/repositories/dedalus-project/dedalus/issues/32/changes/20957132.json"}, "html": {"href": "#!/dedalus-project/dedalus/issues/32#comment-20957132"}}, "issue": {"links": {"self": {"href": "data/repositories/dedalus-project/dedalus/issues/32.json"}}, "type": "issue", "id": 32, "repository": {"links": {"self": {"href": "data/repositories/dedalus-project/dedalus.json"}, "html": {"href": "#!/dedalus-project/dedalus"}, "avatar": {"href": "data/bytebucket.org/ravatar/{1dc39ab6-2798-450d-af2f-e976f94b5794}ts=2009435"}}, "type": "repository", "name": "dedalus", "full_name": "dedalus-project/dedalus", "uuid": "{1dc39ab6-2798-450d-af2f-e976f94b5794}"}, "title": "Not able to install dedalus packages using pip3"}, "created_on": "2015-08-17T06:10:17.553326+00:00", "user": {"display_name": "Hemant Khatri", "uuid": "{9d70ea3a-2250-48bb-8d30-17d3ecc83320}", "links": {"self": {"href": "https://api.bitbucket.org/2.0/users/%7B9d70ea3a-2250-48bb-8d30-17d3ecc83320%7D"}, "html": {"href": "https://bitbucket.org/%7B9d70ea3a-2250-48bb-8d30-17d3ecc83320%7D/"}, "avatar": {"href": "https://bitbucket.org/account/hk310/avatar/"}}, "nickname": "hk310", "type": "user", "account_id": null}, "message": {"raw": null, "markup": "markdown", "html": "", "type": "rendered"}, "type": "issue_change", "id": 20957132}